imdb/__init__.py
imdb/__main__.py
imdb/api.py
imdb/imdb.py
Andrew_Huang-0.1.1.dist-info/LICENSE.txt
Andrew_Huang-0.1.1.dist-info/METADATA
Andrew_Huang-0.1.1.dist-info/WHEEL
Andrew_Huang-0.1.1.dist-info/entry_points.txt
Andrew_Huang-0.1.1.dist-info/top_level.txt
Andrew_Huang-0.1.1.dist-info/RECORD
