Metadata-Version: 2.1
Name: Andrew-Huang
Version: 0.1.1
Summary: Given a imdb id, scrapes the corresponding imdb page and returns the rating
Author-email: Andrew Huang <huan1628@purdue.edu>
Keywords: example,imdb,tutorial
Classifier: License :: OSI Approved :: MIT License
Classifier: Programming Language :: Python
Classifier: Programming Language :: Python :: 3
Classifier: Framework :: FastAPI
License-File: LICENSE.txt
Requires-Dist: lxml (>=4.9.1)
Requires-Dist: requests (>=2.28.1)
Requires-Dist: fastapi (>=0.85.2)
Requires-Dist: Jinja2 (>=3.1.2)
Requires-Dist: uvicorn[standard]
